wikivector/__init__.py
wikivector/vector.py
wikivector/wiki.py
wikivector-1.2.1.data/scripts/embed_articles
wikivector-1.2.1.data/scripts/export_articles
wikivector-1.2.1.data/scripts/read_article
wikivector-1.2.1.data/scripts/wiki_check_map
wikivector-1.2.1.data/scripts/wiki_header
wikivector-1.2.1.data/scripts/wiki_remove_tags
wikivector-1.2.1.dist-info/LICENSE
wikivector-1.2.1.dist-info/METADATA
wikivector-1.2.1.dist-info/WHEEL
wikivector-1.2.1.dist-info/top_level.txt
wikivector-1.2.1.dist-info/RECORD
