Metadata-Version: 2.1
Name: wikivector
Version: 1.2.1
Summary: WikiVector: Tools for encoding Wikipedia articles as vectors
Home-page: https://github.com/mortonne/wikivector
Author: Neal Morton
Author-email: mortonne@gmail.com
License: GPL-3.0-or-later
Keywords: NLP,Wikipedia
Platform: UNKNOWN
Classifier: Programming Language :: Python :: 3
Classifier: License :: OSI Approved :: GNU General Public License v3 or later (GPLv3+)
Classifier: Operating System :: OS Independent
Requires-Dist: numpy
Requires-Dist: selectolax
Requires-Dist: h5py (>=3)
Requires-Dist: pandas
Requires-Dist: tensorflow-hub
